touch_cache/__init__.py
touch_cache/memoize.py
touch_cache/open_track.py
touch_cache-0.1.0.dist-info/licenses/LICENSE
touch_cache-0.1.0.dist-info/METADATA
touch_cache-0.1.0.dist-info/WHEEL
touch_cache-0.1.0.dist-info/top_level.txt
touch_cache-0.1.0.dist-info/RECORD
