Metadata-Version: 2.4
Name: touch_cache
Version: 0.1.0
Summary: touch_cache is a smart memoization library that tracks the files opened during the process. The cache is automatically invalidated when one of the used file is modified (more recent) than the cache.
Author-email: Raphaël Jolivet <raph@rjo.name>
License: MIT
Project-URL: Homepage, https://codeberg.org/raphael-jolivet/touch_cache
Project-URL: Repository, https://codeberg.org/raphael-jolivet/touch_cache.git
Requires-Python: >=3.8
License-File: LICENSE
Requires-Dist: cloudpickle
Provides-Extra: dev
Requires-Dist: pytest>=8.0; extra == "dev"
Dynamic: license-file
